kanstream/__init__.py
kanstream/version.py
kanstream/codec/__init__.py
kanstream/codec/abc.py
kanstream/codec/codec.py
kanstream/codec/h264.py
kanstream/codec/h265.py
kanstream/codec/vp9.py
kanstream/stream/__init__.py
kanstream/stream/base.py
kanstream/stream/frame_pb2.py
kanstream/stream/protobuf.py
kanstream/stream/receiver.py
kanstream/stream/sender.py
kanstream/utils/__init__.py
kanstream/utils/calculate_bitrate.py
kanstream/utils/frame_queue.py
kanstream-2.1.1.dist-info/METADATA
kanstream-2.1.1.dist-info/WHEEL
kanstream-2.1.1.dist-info/top_level.txt
kanstream-2.1.1.dist-info/RECORD
